mt_FileMan/__init__.py
mt_FileMan/mt_FileMan.py
mt_FileMan-0.0.3.dist-info/LICENSE
mt_FileMan-0.0.3.dist-info/METADATA
mt_FileMan-0.0.3.dist-info/WHEEL
mt_FileMan-0.0.3.dist-info/top_level.txt
mt_FileMan-0.0.3.dist-info/RECORD
