Metadata-Version: 2.1
Name: mt-FileMan
Version: 0.0.3
Summary: A package for custom file managing classes and methods for MaxTrack
Home-page: UNKNOWN
Author: mole1000
Author-email: mole1000@protonmail.com
License: UNKNOWN
Platform: UNKNOWN
Classifier: Programming Language :: Python :: 3
Classifier: License :: OSI Approved :: MIT License
Classifier: Operating System :: OS Independent
Requires-Python: >=3.6
Provides-Extra: testing
Requires-Dist: pytest ; extra == 'testing'
